README.md
allenact/__init__.py
allenact/_constants.py
allenact/main.py
allenact/setup.py
allenact.egg-info/PKG-INFO
allenact.egg-info/SOURCES.txt
allenact.egg-info/dependency_links.txt
allenact.egg-info/entry_points.txt
allenact.egg-info/requires.txt
allenact.egg-info/top_level.txt
allenact/algorithms/__init__.py
allenact/algorithms/offpolicy_sync/__init__.py
allenact/algorithms/offpolicy_sync/losses/__init__.py
allenact/algorithms/offpolicy_sync/losses/abstract_offpolicy_loss.py
allenact/algorithms/onpolicy_sync/__init__.py
allenact/algorithms/onpolicy_sync/engine.py
allenact/algorithms/onpolicy_sync/misc.py
allenact/algorithms/onpolicy_sync/policy.py
allenact/algorithms/onpolicy_sync/runner.py
allenact/algorithms/onpolicy_sync/storage.py
allenact/algorithms/onpolicy_sync/vector_sampled_tasks.py
allenact/algorithms/onpolicy_sync/losses/__init__.py
allenact/algorithms/onpolicy_sync/losses/a2cacktr.py
allenact/algorithms/onpolicy_sync/losses/abstract_loss.py
allenact/algorithms/onpolicy_sync/losses/grouped_action_imitation.py
allenact/algorithms/onpolicy_sync/losses/imitation.py
allenact/algorithms/onpolicy_sync/losses/ppo.py
allenact/base_abstractions/__init__.py
allenact/base_abstractions/callbacks.py
allenact/base_abstractions/distributions.py
allenact/base_abstractions/experiment_config.py
allenact/base_abstractions/misc.py
allenact/base_abstractions/preprocessor.py
allenact/base_abstractions/sensor.py
allenact/base_abstractions/task.py
allenact/embodiedai/__init__.py
allenact/embodiedai/aux_losses/__init__.py
allenact/embodiedai/aux_losses/losses.py
allenact/embodiedai/mapping/__init__.py
allenact/embodiedai/mapping/mapping_losses.py
allenact/embodiedai/mapping/mapping_models/__init__.py
allenact/embodiedai/mapping/mapping_models/active_neural_slam.py
allenact/embodiedai/mapping/mapping_utils/__init__.py
allenact/embodiedai/mapping/mapping_utils/map_builders.py
allenact/embodiedai/mapping/mapping_utils/point_cloud_utils.py
allenact/embodiedai/models/__init__.py
allenact/embodiedai/models/aux_models.py
allenact/embodiedai/models/basic_models.py
allenact/embodiedai/models/fusion_models.py
allenact/embodiedai/models/resnet.py
